snailpy/__init__.py
snailpy/goobert.poo
snailpy/snailpy.py
snailpy-1.1.0.dist-info/LICENSE
snailpy-1.1.0.dist-info/METADATA
snailpy-1.1.0.dist-info/WHEEL
snailpy-1.1.0.dist-info/entry_points.txt
snailpy-1.1.0.dist-info/top_level.txt
snailpy-1.1.0.dist-info/RECORD
