Metadata-Version: 2.1
Name: snailpy
Version: 1.1.0
Summary: Use the Snail IDE API in your python scripts.
Author-email: Nolan Simpson <nmsderp@gmail.com>
Maintainer-email: Nolan Simpson <nmsderp@gmail.com>
License: GNU GENERAL PUBLIC LICENSE
Project-URL: Homepage, https://snail-ide.js.org/SnailPy
Project-URL: Repository, https://github.com/Snail-IDE/SnailPy.git
Project-URL: Bug Tracker, https://github.com/Snail-IDE/SnailPy/issues
Keywords: scratch,api
Classifier: Development Status :: 3 - Alpha
Classifier: Programming Language :: Python
Requires-Python: >=3.8
License-File: LICENSE
Requires-Dist: requests
